comyx/__init__.py
comyx/fading/__init__.py
comyx/fading/nakagami.py
comyx/fading/rayleigh.py
comyx/fading/rician.py
comyx/network/__init__.py
comyx/network/base_station.py
comyx/network/links.py
comyx/network/ris.py
comyx/network/transceiver.py
comyx/network/user_equipment.py
comyx/propagation/__init__.py
comyx/propagation/noise.py
comyx/propagation/pathloss.py
comyx/stats/__init__.py
comyx/stats/common.py
comyx/stats/metrics.py
comyx/stats/moments.py
comyx/utils/__init__.py
comyx/utils/utils.py
comyx-0.2.5.dist-info/LICENSE
comyx-0.2.5.dist-info/METADATA
comyx-0.2.5.dist-info/WHEEL
comyx-0.2.5.dist-info/top_level.txt
comyx-0.2.5.dist-info/RECORD
