Metadata-Version: 2.1
Name: comyx
Version: 0.2.5
Summary: Comyx is an optimized and modular Python library for simulating wireless communication systems.
Author-email: Muhammad Umer <thisismumer@gmail.com>
Project-URL: homepage, https://github.com/muhd-umer/comyx
Keywords: python,communication,simulator,wireless communication
Classifier: Development Status :: 3 - Alpha
Classifier: Intended Audience :: Developers
Classifier: Intended Audience :: Science/Research
Classifier: Topic :: Software Development :: Build Tools
Classifier: Programming Language :: Python :: 3
Classifier: Programming Language :: Python :: 3.11
Classifier: Programming Language :: Python :: 3.12
Classifier: Programming Language :: Python :: 3 :: Only
Classifier: License :: OSI Approved :: MIT License
Classifier: Operating System :: OS Independent
Requires-Python: >=3.10
License-File: LICENSE
Requires-Dist: numpy >=1.23.5
Requires-Dist: numba >=0.54.1
Requires-Dist: pandas >=2.0.1
Requires-Dist: scipy >=1.11.1
Requires-Dist: mpmath >=1.3.0
Requires-Dist: colorama >=0.4.6
Requires-Dist: matplotlib >=3.5.1
Requires-Dist: pyarrow >=14.0.0
Requires-Dist: python-box >=7.1.1
Requires-Dist: termcolor >=2.4.0
